SnuggleBunny.py
clear.py
SnuggleBunny-0.0.11.dist-info/METADATA
SnuggleBunny-0.0.11.dist-info/WHEEL
SnuggleBunny-0.0.11.dist-info/top_level.txt
SnuggleBunny-0.0.11.dist-info/RECORD
