Metadata-Version: 2.1
Name: SnuggleBunny
Version: 0.0.11
Summary: SnuggleBunny is a tool used to check the strength of encryption on web servers!
Author: Invizabel
Project-URL: Homepage, https://github.com/Invizabel/SnuggleBunny
Project-URL: Bug Tracker, https://github.com/Invizabel/SnuggleBunny/issues
Classifier: Programming Language :: Python :: 3
Classifier: License :: OSI Approved :: MIT License
Classifier: Operating System :: OS Independent
Requires-Python: >=3.7
